aliyunsdksgw/__init__.py
aliyunsdksgw/endpoint.py
aliyunsdksgw/request/__init__.py
aliyunsdksgw/request/v20180511/AddSharesToExpressSyncRequest.py
aliyunsdksgw/request/v20180511/CreateExpressSyncRequest.py
aliyunsdksgw/request/v20180511/CreateGatewayBlockVolumeRequest.py
aliyunsdksgw/request/v20180511/CreateGatewayCacheDiskRequest.py
aliyunsdksgw/request/v20180511/CreateGatewayFileShareRequest.py
aliyunsdksgw/request/v20180511/CreateGatewayLoggingRequest.py
aliyunsdksgw/request/v20180511/CreateGatewayRequest.py
aliyunsdksgw/request/v20180511/CreateGatewaySMBUserRequest.py
aliyunsdksgw/request/v20180511/CreateStorageBundleRequest.py
aliyunsdksgw/request/v20180511/DeleteExpressSyncRequest.py
aliyunsdksgw/request/v20180511/DeleteGatewayBlockVolumesRequest.py
aliyunsdksgw/request/v20180511/DeleteGatewayCacheDiskRequest.py
aliyunsdksgw/request/v20180511/DeleteGatewayFileSharesRequest.py
aliyunsdksgw/request/v20180511/DeleteGatewayLoggingRequest.py
aliyunsdksgw/request/v20180511/DeleteGatewayRequest.py
aliyunsdksgw/request/v20180511/DeleteGatewaySMBUserRequest.py
aliyunsdksgw/request/v20180511/DeleteStorageBundleRequest.py
aliyunsdksgw/request/v20180511/DeployGatewayRequest.py
aliyunsdksgw/request/v20180511/DescribeAccountConfigRequest.py
aliyunsdksgw/request/v20180511/DescribeExpressSyncSharesRequest.py
aliyunsdksgw/request/v20180511/DescribeExpressSyncsRequest.py
aliyunsdksgw/request/v20180511/DescribeGatewayADInfoRequest.py
aliyunsdksgw/request/v20180511/DescribeGatewayBlockVolumesRequest.py
aliyunsdksgw/request/v20180511/DescribeGatewayCachesRequest.py
aliyunsdksgw/request/v20180511/DescribeGatewayCategoriesRequest.py
aliyunsdksgw/request/v20180511/DescribeGatewayClassesRequest.py
aliyunsdksgw/request/v20180511/DescribeGatewayCredentialRequest.py
aliyunsdksgw/request/v20180511/DescribeGatewayDNSRequest.py
aliyunsdksgw/request/v20180511/DescribeGatewayFileSharesRequest.py
aliyunsdksgw/request/v20180511/DescribeGatewayFileStatusRequest.py
aliyun_python_sdk_sgw-1.0.4.dist-info/LICENSE
aliyun_python_sdk_sgw-1.0.4.dist-info/METADATA
aliyun_python_sdk_sgw-1.0.4.dist-info/WHEEL
aliyun_python_sdk_sgw-1.0.4.dist-info/top_level.txt
aliyun_python_sdk_sgw-1.0.4.dist-info/RECORD
